{
  "last_run_timestamp": "2026-06-13 10:35 PM",
  "success": true,
  "duration_seconds": 1.63,
  "sources": {
    "tungabhadra": {
      "status": "Operational",
      "ok": true,
      "count": 1
    },
    "tamil_nadu": {
      "status": "Operational",
      "ok": true,
      "count": 19
    },
    "oneindia": {
      "status": "Operational",
      "ok": true,
      "count": 15
    }
  },
  "metrics": {
    "dams_changed": 0,
    "storage_delta_tmc": 0.0,
    "inflow_delta_cusecs": 0,
    "outflow_delta_cusecs": 0
  },
  "history": [
    {
      "timestamp": "2026-06-13 10:35 PM",
      "success": true,
      "duration_seconds": 1.63,
      "sources": {
        "tungabhadra": {
          "status": "Operational",
          "ok": true,
          "count": 1
        },
        "tamil_nadu": {
          "status": "Operational",
          "ok": true,
          "count": 19
        },
        "oneindia": {
          "status": "Operational",
          "ok": true,
          "count": 15
        }
      },
      "metrics": {
        "dams_changed": 0,
        "storage_delta_tmc": 0.0,
        "inflow_delta_cusecs": 0,
        "outflow_delta_cusecs": 0
      }
    },
    {
      "timestamp": "2026-06-13 10:00 AM",
      "success": true,
      "duration_seconds": 1.42,
      "sources": {
        "tungabhadra": {
          "status": "Operational",
          "ok": true,
          "count": 1
        },
        "tamil_nadu": {
          "status": "Operational",
          "ok": true,
          "count": 19
        },
        "oneindia": {
          "status": "Operational",
          "ok": true,
          "count": 15
        }
      },
      "metrics": {
        "dams_changed": 35,
        "storage_delta_tmc": 0.428,
        "inflow_delta_cusecs": 4120,
        "outflow_delta_cusecs": -1280
      }
    },
    {
      "timestamp": "2026-06-12 10:00 AM",
      "success": true,
      "duration_seconds": 1.61,
      "sources": {
        "tungabhadra": {
          "status": "Operational",
          "ok": true,
          "count": 1
        },
        "tamil_nadu": {
          "status": "Operational",
          "ok": true,
          "count": 19
        },
        "oneindia": {
          "status": "Operational",
          "ok": true,
          "count": 15
        }
      },
      "metrics": {
        "dams_changed": 32,
        "storage_delta_tmc": -0.152,
        "inflow_delta_cusecs": -1850,
        "outflow_delta_cusecs": 420
      }
    },
    {
      "timestamp": "2026-06-11 10:00 AM",
      "success": true,
      "duration_seconds": 1.38,
      "sources": {
        "tungabhadra": {
          "status": "Operational",
          "ok": true,
          "count": 1
        },
        "tamil_nadu": {
          "status": "Operational",
          "ok": true,
          "count": 19
        },
        "oneindia": {
          "status": "Operational",
          "ok": true,
          "count": 15
        }
      },
      "metrics": {
        "dams_changed": 34,
        "storage_delta_tmc": 0.825,
        "inflow_delta_cusecs": 9400,
        "outflow_delta_cusecs": 1100
      }
    }
  ]
}